value_exception_handler/__init__.py
value_exception_handler/exception_handler.py
value_exception_handler-0.1.0.dist-info/LICENCE
value_exception_handler-0.1.0.dist-info/METADATA
value_exception_handler-0.1.0.dist-info/WHEEL
value_exception_handler-0.1.0.dist-info/top_level.txt
value_exception_handler-0.1.0.dist-info/RECORD
