Metadata-Version: 2.1
Name: value_exception_handler
Version: 0.1.0
Summary: A utility for handling user input validation and exceptions in Python.
Home-page: https://github.com/thidaskaveesha/value_exception_handler
Author: Thidas Senavirathna
Author-email: thidaskaveesha@gmail.com
Classifier: Programming Language :: Python :: 3
Classifier: License :: OSI Approved :: MIT License
Classifier: Operating System :: OS Independent
Requires-Python: >=3.6
License-File: LICENCE
